{
	"parent": "minecraft:recipes/root",
	"rewards": {
		"recipes": [
			"cutandcolored:crafting/brown_stained_plank_stairs_from_planks"
		]
	},
	"criteria": {
		"has_item": {
			"trigger": "minecraft:inventory_changed",
			"conditions": {
				"items": [
					{
						"item": "cutandcolored:brown_stained_planks"
					}
				]
			}
		},
		"has_the_recipe": {
			"trigger": "minecraft:recipe_unlocked",
			"conditions": {
				"recipe": "cutandcolored:crafting/brown_stained_plank_stairs_from_planks"
			}
		}
	},
	"requirements": [
		[
			"has_item",
			"has_the_recipe"
		]
	]
}
