{
  "type": "forge:conditional",
  "recipes": [
    {
      "conditions": [
        {
          "modid": "additionalbarsbop",
          "type": "forge:mod_loaded"
        }
      ],
      "recipe": {
        "type": "cutandcolored:sawmilling",
        "ingredient": [
          {
            "item": "additionalbarsbop:fir_bars"
          },
          {
            "item": "additionalbarsbop:crossed_fir_bars"
          }
        ],
        "result": "additionalbarsbop:horizontal_crossed_fir_bars",
        "count": 1
      }
    }
  ]
}