{
	"conditions": [
		{
			"type": "forge:mod_loaded",
			"modid": "additionalbarsbop"
		},
		{
			"type": "forge:mod_loaded",
			"modid": "biomesoplenty"
		}
	],
	"parent": "minecraft:recipes/root",
	"rewards": {
		"recipes": [
			"cutandcolored:sawmilling/fir_bars"
		]
	},
	"criteria": {
		"has_item": {
			"trigger": "minecraft:inventory_changed",
			"conditions": {
				"items": [
					{
						"tag": "biomesoplenty:fir_logs"
					}
				]
			}
		},
		"has_the_recipe": {
			"trigger": "minecraft:recipe_unlocked",
			"conditions": {
				"recipe": "cutandcolored:sawmilling/fir_bars"
			}
		}
	},
	"requirements": [
		[
			"has_item",
			"has_the_recipe"
		]
	]
}
